cml/__init__.py
cml/admin.py
cml/auth.py
cml/conf.py
cml/items.py
cml/models.py
cml/urls.py
cml/utils.py
cml/views.py
cml/xml.py
cml/management/__init__.py
cml/management/commands/__init__.py
cml/management/commands/cml_init.py
cml/migrations/0001_initial.py
cml/migrations/0002_reorganize_fields.py
cml/migrations/__init__.py
cml/templates/cml/cml_delegate.py
django_cml2-1.0.0.3.dist-info/LICENSE
django_cml2-1.0.0.3.dist-info/METADATA
django_cml2-1.0.0.3.dist-info/WHEEL
django_cml2-1.0.0.3.dist-info/top_level.txt
django_cml2-1.0.0.3.dist-info/RECORD
