Metadata-Version: 2.1
Name: django-cml2
Version: 1.0.0.3
Summary: Application for data exchange in CommerceML 2 standard. This is a new version with new architecture
Home-page: https://github.com/sergey-gru/django-cml2
Author: Sergey Grunenko
Author-email: grunenko.serg@gmail.com
License: BSD License
Platform: UNKNOWN
Classifier: Environment :: Web Environment
Classifier: Framework :: Django
Classifier: Framework :: Django :: 3.2
Classifier: Intended Audience :: Developers
Classifier: License :: OSI Approved :: BSD License
Classifier: Operating System :: OS Independent
Classifier: Programming Language :: Python
Classifier: Programming Language :: Python :: 3.3
Classifier: Programming Language :: Python :: 3.4
Classifier: Programming Language :: Python :: 3.5
Classifier: Topic :: Internet :: WWW/HTTP
Classifier: Topic :: Internet :: WWW/HTTP :: Dynamic Content
Requires-Python: >3.3.0
License-File: LICENSE
Requires-Dist: Django (>=3.2)
Requires-Dist: django-appconf (>=1.0.1)
